neosign/__init__.py
neosign/sign.py
neosign-0.2.2.dist-info/LICENSE.md
neosign-0.2.2.dist-info/METADATA
neosign-0.2.2.dist-info/WHEEL
neosign-0.2.2.dist-info/entry_points.txt
neosign-0.2.2.dist-info/top_level.txt
neosign-0.2.2.dist-info/RECORD
